elpie/__init__.py
elpie/__main__.py
elpie-0.1.1.dist-info/licenses/LICENSE
elpie-0.1.1.dist-info/METADATA
elpie-0.1.1.dist-info/WHEEL
elpie-0.1.1.dist-info/entry_points.txt
elpie-0.1.1.dist-info/top_level.txt
elpie-0.1.1.dist-info/RECORD
