Metadata-Version: 2.4
Name: elpie
Version: 0.1.1
Summary: Emacs-like Python-infused editor
Author-email: Francis Peck <frncspeck@gmail.com>
License: MIT
Keywords: cli,editor,emacs,curses,python
Classifier: Programming Language :: Python :: 3
Classifier: Environment :: Console
Classifier: License :: OSI Approved :: MIT License
Requires-Python: >=3.8
License-File: LICENSE
Dynamic: license-file
